pyethswarm/__init__.py
pyethswarm/address.py
pyethswarm/api.py
pyethswarm/common.py
pyethswarm/debug_api.py
pyethswarm-0.0.3.dist-info/METADATA
pyethswarm-0.0.3.dist-info/WHEEL
pyethswarm-0.0.3.dist-info/top_level.txt
pyethswarm-0.0.3.dist-info/RECORD
